online_fdr/__init__.py
online_fdr/abstract/__init__.py
online_fdr/abstract/abstract_batching_test.py
online_fdr/abstract/abstract_gamma_seq.py
online_fdr/abstract/abstract_sequential_test.py
online_fdr/abstract/abstract_spend_func.py
online_fdr/batching/__init__.py
online_fdr/batching/bh.py
online_fdr/batching/by.py
online_fdr/batching/prds.py
online_fdr/batching/storey_bh.py
online_fdr/investing/__init__.py
online_fdr/investing/addis/__init__.py
online_fdr/investing/addis/addis.py
online_fdr/investing/alpha/__init__.py
online_fdr/investing/alpha/alpha.py
online_fdr/investing/lond/__init__.py
online_fdr/investing/lond/lond.py
online_fdr/investing/lord/__init__.py
online_fdr/investing/lord/dependent.py
online_fdr/investing/lord/discard.py
online_fdr/investing/lord/mem_decay.py
online_fdr/investing/lord/plus_plus.py
online_fdr/investing/lord/three.py
online_fdr/investing/saffron/__init__.py
online_fdr/investing/saffron/saffron.py
online_fdr/naive/__init__.py
online_fdr/naive/naive.py
online_fdr/spending/__init__.py
online_fdr/spending/alpha_spending.py
online_fdr/spending/online_fallback.py
online_fdr/spending/functions/__init__.py
online_fdr/spending/functions/bonferroni.py
online_fdr/spending/functions/lord_three.py
online_fdr/utils/__init__.py
online_fdr/utils/evaluation.py
online_fdr/utils/format.py
online_fdr/utils/generation.py
online_fdr/utils/sequence.py
online_fdr/utils/static.py
online_fdr/utils/testing.py
online_fdr/utils/validity.py
online_fdr-0.0.3.dist-info/METADATA
online_fdr-0.0.3.dist-info/WHEEL
online_fdr-0.0.3.dist-info/licenses/LICENSE
online_fdr-0.0.3.dist-info/RECORD
