Metadata-Version: 2.4
Name: online-fdr
Version: 0.0.3
Summary: Online False Discovery Rate (FDR) control algorithms for multiple hypothesis testing
Project-URL: Homepage, https://github.com/yourusername/online-fdr
Project-URL: Documentation, https://online-fdr.readthedocs.io
Project-URL: Repository, https://github.com/yourusername/online-fdr.git
Project-URL: Issues, https://github.com/yourusername/online-fdr/issues
Project-URL: Changelog, https://github.com/yourusername/online-fdr/blob/main/CHANGELOG.md
Author-email: Oliver Hennhöfer <oliver.hennhoefer@mail.de>
Maintainer-email: Oliver Hennhöfer <oliver.hennhoefer@mail.de>
License-Expression: BSD-3-Clause
License-File: LICENSE
Keywords: batched-testing,false-discovery-rate,fdr,hypothesis-testing,multiple-testing,online-algorithms,sequential-testing,statistics
Classifier: Development Status :: 4 - Beta
Classifier: Intended Audience :: Science/Research
Classifier: License :: OSI Approved :: BSD License
Classifier: Operating System :: OS Independent
Classifier: Programming Language :: Python
Classifier: Programming Language :: Python :: 3
Classifier: Programming Language :: Python :: 3.8
Classifier: Programming Language :: Python :: 3.9
Classifier: Programming Language :: Python :: 3.10
Classifier: Programming Language :: Python :: 3.11
Classifier: Programming Language :: Python :: 3.12
Classifier: Programming Language :: Python :: Implementation :: CPython
Classifier: Topic :: Scientific/Engineering :: Information Analysis
Classifier: Topic :: Scientific/Engineering :: Mathematics
Requires-Python: >=3.8
Requires-Dist: numpy>=1.20.0
Requires-Dist: scipy>=1.9.0
Provides-Extra: data
Requires-Dist: scipy>=1.9.0; extra == 'data'
Provides-Extra: dev
Requires-Dist: black>=23.0; extra == 'dev'
Requires-Dist: mypy>=1.0; extra == 'dev'
Requires-Dist: pytest-cov>=4.0; extra == 'dev'
Requires-Dist: pytest>=7.0; extra == 'dev'
Requires-Dist: ruff>=0.1.0; extra == 'dev'
Requires-Dist: scipy>=1.9.0; extra == 'dev'
Provides-Extra: docs
Requires-Dist: myst-parser>=0.18; extra == 'docs'
Requires-Dist: sphinx-rtd-theme>=1.0; extra == 'docs'
Requires-Dist: sphinx>=5.0; extra == 'docs'
